{
  "packageId": "ch.orbit.rp",
  "host": "rowing.joaro.ch",
  "name": "Rowing Player",
  "launcherName": "RP",
  "display": "standalone",
  "themeColor": "#0C66C7",
  "themeColorDark": "#000000",
  "navigationColor": "#000000",
  "navigationColorDark": "#000000",
  "navigationDividerColor": "#000000",
  "navigationDividerColorDark": "#000000",
  "backgroundColor": "#2A2C34",
  "enableNotifications": true,
  "startUrl": "/",
  "iconUrl": "https://rowing.joaro.ch/rowingplayer.svg",
  "splashScreenFadeOutDuration": 300,
  "signingKey": {
    "path": "/app/android.keystore",
    "alias": "android"
  },
  "appVersionName": "10",
  "appVersionCode": 10,
  "shortcuts": [],
  "generatorApp": "bubblewrap-cli",
  "webManifestUrl": "https://rowing.joaro.ch/rowingplayer.json",
  "fallbackType": "customtabs",
  "features": {},
  "alphaDependencies": {
    "enabled": false
  },
  "enableSiteSettingsShortcut": true,
  "isChromeOSOnly": false,
  "isMetaQuest": false,
  "fullScopeUrl": "https://rowing.joaro.ch/",
  "minSdkVersion": 21,
  "orientation": "portrait",
  "fingerprints": [],
  "additionalTrustedOrigins": [],
  "retainedBundles": [],
  "protocolHandlers": [],
  "fileHandlers": [],
  "launchHandlerClientMode": "",
  "displayOverride": [],
  "appVersion": "10"
}